{
    "easy": [
        {
            "image": "images/hidden_puzzle.webp",
            "objects": [
                {
                    "name": "빨간 사과",
                    "x": 171,
                    "y": 100,
                    "width": 50,
                    "height": 50
                },
                {
                    "name": "노란 나비",
                    "x": 853,
                    "y": 311,
                    "width": 50,
                    "height": 50
                },
                {
                    "name": "파란 공",
                    "x": 709,
                    "y": 374,
                    "width": 50,
                    "height": 50
                },
                {
                    "name": "초록 잎",
                    "x": 34,
                    "y": 409,
                    "width": 50,
                    "height": 50
                },
                {
                    "name": "보라색 모자",
                    "x": 618,
                    "y": 708,
                    "width": 50,
                    "height": 50
                }
            ]
        },
        {
            "image": "images/find_hidden_pictures_054.jpg",
            "objects": [
                {
                    "name": "신발",
                    "x": 563,
                    "y": 94,
                    "width": 50,
                    "height": 50
                },
                {
                    "name": "도자기",
                    "x": 652,
                    "y": 537,
                    "width": 50,
                    "height": 50
                },
                {
                    "name": "선인장",
                    "x": 457,
                    "y": 275,
                    "width": 50,
                    "height": 50
                },
                {
                    "name": "물병",
                    "x": 650,
                    "y": 209,
                    "width": 50,
                    "height": 50
                },
                {
                    "name": "칼",
                    "x": 208,
                    "y": 665,
                    "width": 50,
                    "height": 50
                },
                {
                    "name": "숱가락",
                    "x": 98,
                    "y": 281,
                    "width": 50,
                    "height": 50
                }
            ]
        }
    ],
    "medium": [],
    "hard": []
}
