{"word": "pray ", "meaning": "빌다, 기도하다", "difficulty": "hard"},
{"word": "reflect ", "meaning": "반사하다, 반영하다, 숙고하다", "difficulty": "hard"},
{"word": "ascend ", "meaning": "올라가다", "difficulty": "hard"},
{"word": "descend ", "meaning": "내려오다", "difficulty": "hard"},
{"word": "embark", "meaning": "배를 타다, 시작하다", "difficulty": "hard"},
{"word": "mention ", "meaning": "말하다, 언급하다", "difficulty": "hard"},
{"word": "quote ", "meaning": "인용하다", "difficulty": "hard"},
{"word": "occupy ", "meaning": "차지하다, 종사하다", "difficulty": "hard"},
{"word": "surround ", "meaning": "둘러싸다", "difficulty": "hard"},
{"word": "avail ", "meaning": "쓸모있다, 소용되다 #명 쓸모, 이익", "difficulty": "hard"},
{"word": "preach ", "meaning": "설교하다", "difficulty": "hard"},
{"word": "retire ", "meaning": "물러나다, 은퇴하다", "difficulty": "hard"},
{"word": "argue ", "meaning": "논하다, 설득하다", "difficulty": "hard"},
{"word": "graduate ", "meaning": "졸업하다/ 졸업생", "difficulty": "hard"},
{"word": "affect ", "meaning": "영향을 주다, 감동시키다, ...인 체하다", "difficulty": "hard"},
{"word": "unify ", "meaning": "통일하다", "difficulty": "hard"},
{"word": "operate ", "meaning": "움직이다, 운영하다, 수술하다", "difficulty": "hard"},
{"word": "condemn ", "meaning": "비난하다, (형을)선고하다", "difficulty": "hard"},
{"word": "praise ", "meaning": "칭찬하다 #명 칭찬", "difficulty": "hard"},
{"word": "forgive ", "meaning": "용서하다", "difficulty": "hard"},
{"word": "deserve ", "meaning": " ...할 가치가 있다, ...을 할만하다", "difficulty": "hard"},
{"word": "correspond ", "meaning": "일치하다, 편지를 주고받다", "difficulty": "hard"},
{"word": "explore ", "meaning": "탐험하다", "difficulty": "hard"},
{"word": "recollect ", "meaning": "회상하다", "difficulty": "hard"},
{"word": "fascinate ", "meaning": "매혹하다", "difficulty": "hard"},
{"word": "stir ", "meaning": "휘젓다, 움직이다", "difficulty": "hard"},
{"word": "exploit", "meaning": "개발하다, 이용하다/공훈, 위업", "difficulty": "hard"},
{"word": "contradict ", "meaning": "반박하다, 모순되다", "difficulty": "hard"},
{"word": "develop ", "meaning": "발달하다, 개발하다", "difficulty": "hard"},
{"word": "approach ", "meaning": "접근하다 #명 접근", "difficulty": "hard"},
{"word": "classify ", "meaning": "분류하다", "difficulty": "hard"},
{"word": "represent ", "meaning": "나타내다, 대표하다, 묘사하다", "difficulty": "hard"},
{"word": "reduce ", "meaning": "줄이다, ...으로 돌아가게 하다", "difficulty": "hard"},
{"word": "wither ", "meaning": "시들다, 말라죽다", "difficulty": "hard"},
{"word": "astonish ", "meaning": "놀라게 하다", "difficulty": "hard"},
{"word": "commit ", "meaning": "맡기다, 범하다", "difficulty": "hard"},
{"word": "claim ", "meaning": "요구(하다), 주장(하다), 권리", "difficulty": "hard"},
{"word": "seclude ", "meaning": "은퇴시키다, 분리시키다", "difficulty": "hard"},
{"word": "appoint ", "meaning": "임명하다, 지정하다", "difficulty": "hard"},
{"word": "animate ", "meaning": "활기를 주다, 고무하다", "difficulty": "hard"},
{"word": "apply ", "meaning": "적용하다, 전념하다, 신청(지원)하다", "difficulty": "hard"},
{"word": "disappoint ", "meaning": "실망시키다", "difficulty": "hard"},
{"word": "trespass ", "meaning": "침해하다, 침입하다", "difficulty": "hard"},
{"word": "decide ", "meaning": "결정하다, 결심하다", "difficulty": "hard"},
{"word": "afford ", "meaning": "주다, ...할 여유가 있다", "difficulty": "hard"},
{"word": "compete ", "meaning": "경쟁하다", "difficulty": "hard"},
{"word": "perceive ", "meaning": "지각하다, 이해하다, 간파하다", "difficulty": "hard"},
{"word": "enchant ", "meaning": "매혹시키다", "difficulty": "hard"},
{"word": "consider ", "meaning": "숙고하다, ...이라고 생각하다", "difficulty": "hard"},
{"word": "transform ", "meaning": "변형하다", "difficulty": "hard"},
{"word": "amaze ", "meaning": "몹시 놀라게 하다", "difficulty": "hard"},
{"word": "expose ", "meaning": "드러내다, 폭로하다", "difficulty": "hard"},
{"word": "emancipate", "meaning": "해방하다", "difficulty": "hard"},
{"word": "penetrate ", "meaning": "꿰뚫다, 간파하다", "difficulty": "hard"},
{"word": "extend ", "meaning": "넓히다, 뻗치다, ...에 이르다", "difficulty": "hard"},
{"word": "reside ", "meaning": "살다, 존재하다", "difficulty": "hard"},
{"word": "confine ", "meaning": "제한하다, 가두다 / 경계, 한도", "difficulty": "hard"},
{"word": "exhibit ", "meaning": "보이다, 전시하다 #명 전시(물)", "difficulty": "hard"},
{"word": "extract ", "meaning": "뽑다.", "difficulty": "hard"},
{"word": "imply ", "meaning": "의미하다, 암시하다", "difficulty": "hard"},
{"word": "determine ", "meaning": "결정하다, 결심하다", "difficulty": "hard"},
{"word": "indicate ", "meaning": "지시하다, 나타내다", "difficulty": "hard"},
{"word": "confront ", "meaning": "직면하다", "difficulty": "hard"},
{"word": "pierce ", "meaning": "꿰뚫다, 간파하다", "difficulty": "hard"},
{"word": "dread ", "meaning": "두려워하다 #명 공포", "difficulty": "hard"},
{"word": "foster ", "meaning": "기르다, (성장을)촉진하다 #형 길러주는", "difficulty": "hard"},
{"word": "cease ", "meaning": "끝내다, 중지하다", "difficulty": "hard"},
{"word": "convey ", "meaning": "나르다, 전하다", "difficulty": "hard"},
{"word": "rescue ", "meaning": "구하다 #명 구조", "difficulty": "hard"},
{"word": "dismiss ", "meaning": "해고하다, 해산하다, 내쫓다", "difficulty": "hard"},
{"word": "disturb ", "meaning": "방해하다", "difficulty": "hard"},
{"word": "incline ", "meaning": "기울이다, 마음이 기울다 #명 경사", "difficulty": "hard"},
{"word": "illustrate ", "meaning": "예증하다, 설명하다, 그림(삽화)을 넣다", "difficulty": "hard"},
{"word": "excel ", "meaning": "(남보다) 낫다", "difficulty": "hard"},
{"word": "mold ", "meaning": "틀에 넣어 만들다 #명 틀, 성질", "difficulty": "hard"},
{"word": "taint ", "meaning": "더럽히다 #명 오염", "difficulty": "hard"},
{"word": "discharge ", "meaning": "짐을 내리다, 면제하다, 해방하다", "difficulty": "hard"},
{"word": "exceed ", "meaning": "넘다, 능가하다", "difficulty": "hard"},
{"word": "usher ", "meaning": "안내하다 #명 수위", "difficulty": "hard"},
{"word": "owe ", "meaning": "은혜를 입고 있다, 빚이있다", "difficulty": "hard"},
{"word": "heed ", "meaning": "주의하다 #명 주의", "difficulty": "hard"},
{"word": "resemble ", "meaning": " ...을 닮다", "difficulty": "hard"},
{"word": "compose ", "meaning": "구성하다 (마음을)가라앉히다", "difficulty": "hard"},
{"word": "refrain ", "meaning": "~을 그만두다, 삼가다", "difficulty": "hard"},
{"word": "relax ", "meaning": "늦추다, 쉬다", "difficulty": "hard"},
{"word": "subscribe ", "meaning": "서명하다, 기부하다, 구독하다", "difficulty": "hard"},
{"word": "interfere ", "meaning": "간섭하다, 방해하다", "difficulty": "hard"},
{"word": "share ", "meaning": "분배하다, 분담하다 #명 몫, 분담", "difficulty": "hard"},
{"word": "injure ", "meaning": "해치다, 상처를 입히다", "difficulty": "hard"},
{"word": "depend ", "meaning": "~에 의지하다", "difficulty": "hard"},
{"word": "disperse ", "meaning": "퍼뜨리다, 흩어지다", "difficulty": "hard"},
{"word": "remove ", "meaning": "이사하다, 제거하다", "difficulty": "hard"},
{"word": "realize ", "meaning": "깨닫다, 실현하다", "difficulty": "hard"},
{"word": "cultivate ", "meaning": "경작하다, 기르다", "difficulty": "hard"},
{"word": "sum ", "meaning": "합계하다, 요약하다 #명 합계, 요점", "difficulty": "hard"},
{"word": "throng ", "meaning": "떼지어 모이다 #명 군중", "difficulty": "hard"},
{"word": "scatter ", "meaning": "뿌리다, 흩어지게하다", "difficulty": "hard"},
{"word": "modify ", "meaning": "변경하다, 수식하다, 완화하다", "difficulty": "hard"},
{"word": "offend ", "meaning": "자 화나게 하다, 범하다", "difficulty": "hard"},
{"word": "associate ", "meaning": "교제하다, 연상하다 #명 동료", "difficulty": "hard"},
{"word": "locate", "meaning": "위치를 정하다, 위치를 알아내다", "difficulty": "hard"},
{"word": "depict", "meaning": "그리다, 묘사하다", "difficulty": "hard"},
{"word": "venture ", "meaning": "감히...하다", "difficulty": "hard"},
{"word": "collect ", "meaning": "모으다, 수집하다", "difficulty": "hard"},
{"word": "grumble", "meaning": "불평하다", "difficulty": "hard"},
{"word": "spoil ", "meaning": "망치다, 손상하다", "difficulty": "hard"},
{"word": "mock ", "meaning": "비웃다/조롱 /모의의", "difficulty": "hard"},
{"word": "recall ", "meaning": "상기하다, 소환하다/회상, 소환", "difficulty": "hard"},
{"word": "reproduce ", "meaning": "재생하다, 번식하다", "difficulty": "hard"},
{"word": "assemble ", "meaning": "모이다 ", "difficulty": "hard"},
{"word": "retreat ", "meaning": "물러가다 /후퇴, 피난처", "difficulty": "hard"},
{"word": "punish ", "meaning": "처벌하다", "difficulty": "hard"},
{"word": "settle ", "meaning": "정착하다, 해결하다", "difficulty": "hard"},
{"word": "conceive ", "meaning": "마음에 품다, 상상하다", "difficulty": "hard"},
{"word": "disclose ", "meaning": "드러내다, 폭로하다", "difficulty": "hard"},
{"word": "repair ", "meaning": "수리(하다)", "difficulty": "hard"},
{"word": "repeat ", "meaning": "되풀이하다", "difficulty": "hard"},
{"word": "degrade ", "meaning": "지위를 낮추다, 품위를 떨어뜨리다", "difficulty": "hard"},
{"word": "amuse ", "meaning": "재미나게 하다", "difficulty": "hard"},
{"word": "obtain ", "meaning": "얻다", "difficulty": "hard"},
{"word": "inform ", "meaning": "알리다", "difficulty": "hard"},
{"word": "curse ", "meaning": "저주하다/ 저주", "difficulty": "hard"},
{"word": "provide ", "meaning": "...을 주다, 준비하다", "difficulty": "hard"},
{"word": "refresh ", "meaning": "상쾌하게 하다, 새롭게 하다", "difficulty": "hard"},
{"word": "manage ", "meaning": "관리하다, 이럭저럭...하다", "difficulty": "hard"},
{"word": "confess ", "meaning": "자백하다, 자인하다", "difficulty": "hard"},
{"word": "demonstrate ", "meaning": "증명하다, 시위하다", "difficulty": "hard"},
{"word": "profess ", "meaning": "공언하다, ...이라고 자칭하다", "difficulty": "hard"},
{"word": "fade ", "meaning": "(색이) 바래다, 시들다", "difficulty": "hard"},
{"word": "manufacture ", "meaning": "제조(하다), 제품", "difficulty": "hard"},
{"word": "appeal ", "meaning": "호소(하다), 간청하다", "difficulty": "hard"},
{"word": "publish ", "meaning": "발표하다, 출판하다", "difficulty": "hard"},
{"word": "interpret ", "meaning": "통역하다, 해석하다", "difficulty": "hard"},
{"word": "entitle ", "meaning": "권리(자격)를 주다", "difficulty": "hard"},
{"word": "disregard ", "meaning": "무시(하다), 경시(하다)", "difficulty": "hard"},
{"word": "ascribe ", "meaning": "(원인을)으로 돌리다(~to)..탓으로 돌리다", "difficulty": "hard"},
{"word": "protect ", "meaning": "보호하다", "difficulty": "hard"},
{"word": "accommodate ", "meaning": "수용하다, 편의를 도모하다", "difficulty": "hard"},
{"word": "overtake ", "meaning": "...을 뒤따라 잡다, 덮치다", "difficulty": "hard"},
{"word": "assist ", "meaning": "돕다", "difficulty": "hard"},
{"word": "support ", "meaning": "지지(하다), 부양(하다)", "difficulty": "hard"},
{"word": "advocate", "meaning": "변호하다, 주장하다", "difficulty": "hard"},
{"word": "attempt ", "meaning": "시도하다 #명 시도", "difficulty": "hard"},
{"word": "partake ", "meaning": " ...에 관여하다, 참가하다", "difficulty": "hard"},
{"word": "greet ", "meaning": "인사하다", "difficulty": "hard"},
{"word": "suggest ", "meaning": "암시하다, 제안하다", "difficulty": "hard"},
{"word": "waste ", "meaning": "낭비하다/ 황폐한", "difficulty": "hard"},
{"word": "reap ", "meaning": "베다, 수확하다", "difficulty": "hard"},
{"word": "dissolve ", "meaning": " ...을 녹이다, 해산하다(시키다)", "difficulty": "hard"},
{"word": "oblige ", "meaning": "부득이...하게 하다, 고맙게 여기다", "difficulty": "hard"},
{"word": "decline ", "meaning": "거절하다, 쇠퇴(하다), 기울다/경사", "difficulty": "hard"},
{"word": "accustom ", "meaning": "익히다, 습관을 붙이다", "difficulty": "hard"},
{"word": "defeat ", "meaning": "패배(시키다), ~에 이기다", "difficulty": "hard"},
{"word": "tempt ", "meaning": "유혹하다", "difficulty": "hard"},
{"word": "exempt ", "meaning": "면제하다 / 면제된", "difficulty": "hard"},
{"word": "induce ", "meaning": "권유하다, 설득하여...시키다", "difficulty": "hard"},
{"word": "oppress ", "meaning": "압박하다", "difficulty": "hard"},
{"word": "acquaint ", "meaning": "알리다", "difficulty": "hard"},
{"word": "impoverish ", "meaning": "가난하게 하다, 쇠약하게 되다", "difficulty": "hard"},
{"word": "resent ", "meaning": "분개하다", "difficulty": "hard"},
{"word": "abuse ", "meaning": "남용(하다), 학대(하다) ", "difficulty": "hard"},
{"word": "bother ", "meaning": "괴롭히다, 걱정하다 / 성가심", "difficulty": "hard"},
{"word": "shrink ", "meaning": "줄다, 오그라들다", "difficulty": "hard"},
{"word": "compel ", "meaning": "억지로...시키다", "difficulty": "hard"},
{"word": "deliver ", "meaning": "배달하다, 연설하다, 아이를 낳다", "difficulty": "hard"},
{"word": "register ", "meaning": "등록하다, 가리키다", "difficulty": "hard"},
{"word": "coincide ", "meaning": "일치하다, 부합하다", "difficulty": "hard"},
{"word": "complicate ", "meaning": "복잡하게 하다", "difficulty": "hard"},
{"word": "astound", "meaning": "깜짝 놀라게 하다", "difficulty": "hard"},
{"word": "discern ", "meaning": "분간하다, 식별하다", "difficulty": "hard"},
{"word": "dispute ", "meaning": "논쟁(하다)", "difficulty": "hard"},
{"word": "remark ", "meaning": "말하다, 주목하다/ 말", "difficulty": "hard"},
{"word": "supplement ", "meaning": "보충(하다)", "difficulty": "hard"},
{"word": "debate ", "meaning": "논쟁(하다), 토론(하다)", "difficulty": "hard"},
{"word": "humiliate ", "meaning": "창피를 주다, 모욕하다", "difficulty": "hard"},
{"word": "contend", "meaning": "다투다, 논쟁하다", "difficulty": "hard"},
{"word": "explode ", "meaning": "폭발하다", "difficulty": "hard"},
{"word": "narrate ", "meaning": "이야기하다", "difficulty": "hard"},
{"word": "administer ", "meaning": "관리하다, 시행하다, 경영하다", "difficulty": "hard"},
{"word": "haunt ", "meaning": "자주 가다, 늘 따라다니다", "difficulty": "hard"},
{"word": "dispense ", "meaning": "나눠주다, ...없이 지내다", "difficulty": "hard"},
{"word": "differ ", "meaning": "다르다", "difficulty": "hard"},
{"word": "eliminate ", "meaning": "제거하다", "difficulty": "hard"},
{"word": "dwell ", "meaning": "살다, 거주하다", "difficulty": "hard"},
{"word": "assume ", "meaning": "~체 하다, 생각하다, 가정하다, 떠맡다", "difficulty": "hard"},
{"word": "apprehend ", "meaning": "염려하다, 체포하다, 이해하다", "difficulty": "hard"},
{"word": "capture ", "meaning": "사로잡다/ 포획", "difficulty": "hard"},
{"word": "rear ", "meaning": "기르다, 세우다 / 후방의; 후방", "difficulty": "hard"},
{"word": "stare ", "meaning": "뚫어지게 보다", "difficulty": "hard"},
{"word": "confer ", "meaning": "수여하다, 의논하다, 참조하다", "difficulty": "hard"},
{"word": "discard ", "meaning": "버리다", "difficulty": "hard"},
{"word": "negotiate ", "meaning": "교섭하다", "difficulty": "hard"},
{"word": "anticipate ", "meaning": "예상하다", "difficulty": "hard"},
{"word": "contrive ", "meaning": "연구해내다, 고안하다, 꾸미다", "difficulty": "hard"},
{"word": "consent", "meaning": "동의(하다), 승낙(하다)", "difficulty": "hard"},
{"word": "defy ", "meaning": "도전하다, 무시하다", "difficulty": "hard"},
{"word": "beware ", "meaning": "조심하다 (~of)", "difficulty": "hard"},
{"word": "summon ", "meaning": "소환하다, (용기, 힘 따위를)내다", "difficulty": "hard"},
{"word": "thrive ", "meaning": "번영하다, 무성하다", "difficulty": "hard"},
{"word": "subdue ", "meaning": "진압하다, 완화하다", "difficulty": "hard"},
{"word": "bloom ", "meaning": "꽃(피다)", "difficulty": "hard"},
{"word": "discriminate ", "meaning": "차별하다, 구별하다", "difficulty": "hard"},
{"word": "sustain ", "meaning": "떠받치다, 부양하다, 견디다", "difficulty": "hard"},
{"word": "enforce ", "meaning": "실시하다, 강제하다, 단속하다", "difficulty": "hard"},
{"word": "transact ", "meaning": "처리하다, 거래하다", "difficulty": "hard"},
{"word": "cling ", "meaning": "달라붙다, 고수하다, 집착하다", "difficulty": "hard"},
{"word": "entrust ", "meaning": "위임하다", "difficulty": "hard"},
{"word": "adhere ", "meaning": "들러붙다, 고수하다, 견지하다", "difficulty": "hard"},
{"word": "transmit ", "meaning": "보내다, 전달하다", "difficulty": "hard"},
{"word": "infect ", "meaning": "전염시키다", "difficulty": "hard"},
{"word": "wrap ", "meaning": "싸다, 포장하다", "difficulty": "hard"},
{"word": "inflict ", "meaning": "(형벌, 고통, 손해를)주다", "difficulty": "hard"},
{"word": "undergo ", "meaning": "(수술, 시험 따위를) 받다, 당하다, 겪다", "difficulty": "hard"},
{"word": "withstand ", "meaning": "저항하다", "difficulty": "hard"},
{"word": "withhold ", "meaning": "보류하다, 억제하다", "difficulty": "hard"},
{"word": "adorn ", "meaning": "장식하다", "difficulty": "hard"},
{"word": "accumulate ", "meaning": "쌓아 올리다, 축적하다", "difficulty": "hard"},
{"word": "behold", "meaning": "보다", "difficulty": "hard"},
{"word": "provoke ", "meaning": "화나게 하다, 도발하다", "difficulty": "hard"},
{"word": "intoxicate", "meaning": "취하게하다", "difficulty": "hard"},
{"word": "rebuke ", "meaning": "비난(하다)", "difficulty": "hard"},
{"word": "confirm ", "meaning": " 확인하다", "difficulty": "hard"},
{"word": "conform ", "meaning": "일치시키다(하다)", "difficulty": "hard"},
{"word": "aspire ", "meaning": "열망하다", "difficulty": "hard"},
{"word": "detach ", "meaning": "떼어놓다, 파견하다", "difficulty": "hard"},
{"word": "rebel ", "meaning": "반역하다, 반항하다 / 반역자", "difficulty": "hard"},
{"word": "trim", "meaning": "정돈하다, 손질하다", "difficulty": "hard"},
{"word": "repel ", "meaning": "쫓아버리다, 불쾌감을 주다", "difficulty": "hard"},
{"word": "lurk", "meaning": "숨어 있다", "difficulty": "hard"},
{"word": "annihilate ", "meaning": "전멸시키다", "difficulty": "hard"},
{"word": "allude ", "meaning": "언급하다, 암시하다", "difficulty": "hard"},
{"word": "sting ", "meaning": "찌르다 / (동물의) 침, 고통", "difficulty": "hard"},
{"word": "allure ", "meaning": "유혹하다", "difficulty": "hard"},
{"word": "replace ", "meaning": "...을 대신하다, 제 자리에 두다", "difficulty": "hard"},
{"word": "console ", "meaning": "위로하다(=solace)", "difficulty": "hard"},
{"word": "surmount ", "meaning": "극복하다", "difficulty": "hard"},
{"word": "treat ", "meaning": "다루다, 대접하다/대접, 환대", "difficulty": "hard"},
{"word": "swell ", "meaning": "부풀다/ 부풀기", "difficulty": "hard"},
{"word": "sneer ", "meaning": "비웃다, 냉소하다(~at)", "difficulty": "hard"},
{"word": "befall ", "meaning": "일어나다, 신변에 닥치다", "difficulty": "hard"},
{"word": "subside ", "meaning": " (비, 바람 따위가) 가라앉다", "difficulty": "hard"},
{"word": "seize ", "meaning": "붙잡다 (=grasp)", "difficulty": "hard"},
{"word": "abandon ", "meaning": "버리다 (=give up)", "difficulty": "hard"},
{"word": "deal ", "meaning": "분배하다, 거래하다, 취급하다", "difficulty": "hard"},
{"word": "steer ", "meaning": "조종하다, 나아가다", "difficulty": "hard"},
{"word": "depress ", "meaning": "낙담시키다, 우울하게하다, 불경기가되게하다", "difficulty": "hard"},
{"word": "inhabit ", "meaning": " ...에 살다, ...에 거주하다", "difficulty": "hard"},
{"word": "grant ", "meaning": "허락하다, 주다, 인정하다", "difficulty": "hard"},
{"word": "attract ", "meaning": "끌다", "difficulty": "hard"},
{"word": "introduce ", "meaning": "소개하다, 도입하다", "difficulty": "hard"},
{"word": "portray ", "meaning": "그리다", "difficulty": "hard"},
{"word": "guarantee ", "meaning": "보증하다 (=warrant) #명 보증(인)", "difficulty": "hard"},
{"word": "regulate ", "meaning": "규정하다, 조절하다", "difficulty": "hard"},
{"word": "presume ", "meaning": "상상하다, 생각하다", "difficulty": "hard"},
{"word": "resume ", "meaning": "다시 시작하다, 되찾다", "difficulty": "hard"},
{"word": "neglect", "meaning": "게을리 하다, 무시하다, 방치하다", "difficulty": "hard"},
{"word": "delay", "meaning": "연기(하다), 지체(하다)", "difficulty": "hard"},
{"word": "assent", "meaning": "동의(하다)", "difficulty": "hard"},
{"word": "dissent", "meaning": "의견을 달리하다 / 불찬성", "difficulty": "hard"},
{"word": "plead", "meaning": "변호하다, 탄원하다", "difficulty": "hard"},
{"word": "reserve", "meaning": "비축하다, 예약하다 / 예약, 사양", "difficulty": "hard"},
{"word": "dictate", "meaning": "구술하다, 명령하다", "difficulty": "hard"},
{"word": "award ", "meaning": "(심사하여)주다, 수여하다 #명 상, 상품, 판정", "difficulty": "hard"},
{"word": "multiply ", "meaning": "증가하다, (수를)곱하다", "difficulty": "hard"},
{"word": "spare ", "meaning": "절약하다, 아끼다/ 예비의", "difficulty": "hard"},
{"word": "grudge ", "meaning": "아까워하다, ...하기를 싫어하다", "difficulty": "hard"},
{"word": "execute ", "meaning": "실행하다, 사형시키다", "difficulty": "hard"},
{"word": "imprison ", "meaning": "...을 교도소에 넣다, 투옥하다", "difficulty": "hard"},
{"word": "proceed ", "meaning": "나아가다, 계속하다", "difficulty": "hard"},
{"word": "recede ", "meaning": "물러가다", "difficulty": "hard"},
{"word": "ponder ", "meaning": "...을 깊이 생각하다", "difficulty": "hard"},
{"word": "scratch ", "meaning": "할퀴다, 긁다", "difficulty": "hard"},
{"word": "embrace ", "meaning": "...을 껴안다, 포옹하다", "difficulty": "hard"},
{"word": "reckon ", "meaning": "계산하다, ...라고 생각하다", "difficulty": "hard"},
{"word": "throb ", "meaning": "(심장이)뛰다, 두근거리다/ 맥박, 고동", "difficulty": "hard"},
{"word": "suppress ", "meaning": "억압하다, (사실을)감추다", "difficulty": "hard"},
{"word": "preoccupy ", "meaning": "마음을 빼앗다, 먼저 차지하다", "difficulty": "hard"},
{"word": "salute ", "meaning": "인사(하다), 경례", "difficulty": "hard"},
{"word": "revise ", "meaning": "개정하다", "difficulty": "hard"},
{"word": "lessen ", "meaning": "적어지다, 적게 하다", "difficulty": "hard"},
{"word": "muse", "meaning": "명상하다, 곰곰히생각하다", "difficulty": "hard"},
{"word": "bid ", "meaning": "명령하다, 말하다", "difficulty": "hard"},
{"word": "concede ", "meaning": "양보하다", "difficulty": "hard"},
{"word": "lade ", "meaning": "싣다", "difficulty": "hard"},
{"word": "deplore ", "meaning": "한탄하다", "difficulty": "hard"},
{"word": "precede ", "meaning": " ...에 앞서다, 능가하다", "difficulty": "hard"},
{"word": "banish ", "meaning": "추방하다(=expel)", "difficulty": "hard"},
{"word": "stifle ", "meaning": "숨막히게 하다, 억누르다", "difficulty": "hard"},
{"word": "abound ", "meaning": "풍부하다", "difficulty": "hard"},
{"word": "deposit ", "meaning": "맡기다/ 예금, 맡긴 것", "difficulty": "hard"},
{"word": "withdraw ", "meaning": "물러나다, 탈퇴하다, (예금을)인출하다", "difficulty": "hard"},
{"word": "retain", "meaning": "보유하다, 간직하다", "difficulty": "hard"},
{"word": "sob", "meaning": "흐느껴 울다", "difficulty": "hard"},
{"word": "reprove ", "meaning": "비난하다, 꾸짖다", "difficulty": "hard"},
{"word": "ally ", "meaning": "동맹하다 /동맹자(국)", "difficulty": "hard"},
{"word": "renounce ", "meaning": "포기하다, 버리다", "difficulty": "hard"},
{"word": "allot ", "meaning": "할당하다", "difficulty": "hard"},
{"word": "assign ", "meaning": "할당하다", "difficulty": "hard"},
{"word": "vow ", "meaning": "맹세(하다)", "difficulty": "hard"},
{"word": "vouch ", "meaning": "보증하다", "difficulty": "hard"},
{"word": "carve ", "meaning": "조각하다", "difficulty": "hard"},
{"word": "verify ", "meaning": "증명하다, 확인하다", "difficulty": "hard"},
{"word": "avenge ", "meaning": "복수하다", "difficulty": "hard"},
{"word": "beckon ", "meaning": "(손짓 따위로) 부르다, 신호하다", "difficulty": "hard"},
{"word": "collapse ", "meaning": "붕괴(하다)", "difficulty": "hard"},
{"word": "mar ", "meaning": "상하게 하다", "difficulty": "hard"},
{"word": "kneel ", "meaning": "무릎끓다, 굴복하다", "difficulty": "hard"},
{"word": "pant ", "meaning": "헐떡이다, 갈망하다(~for)", "difficulty": "hard"},
{"word": "warrant ", "meaning": "보증(하다)", "difficulty": "hard"},
{"word": "kindle ", "meaning": "불을 붙이다", "difficulty": "hard"},
{"word": "uphold ", "meaning": "지지하다, 찬성하다", "difficulty": "hard"},
{"word": "prescribe ", "meaning": "규정하다, 처방하다", "difficulty": "hard"},
{"word": "accompany ", "meaning": "동반하다, (음악)반주하다", "difficulty": "hard"},
{"word": "abide ", "meaning": "살다, 머무르다", "difficulty": "hard"},
{"word": "divide ", "meaning": "나누다, 분할하다", "difficulty": "hard"},
{"word": "paralyze", "meaning": "마비시키다", "difficulty": "hard"},
{"word": "contain ", "meaning": "포함하다", "difficulty": "hard"},
{"word": "endow ", "meaning": "기부하다, 주다", "difficulty": "hard"},
{"word": "guard ", "meaning": "지키다, 조심하다 / 경제, 보호", "difficulty": "hard"},
{"word": "ordain", "meaning": "명령하다, 운명지우다", "difficulty": "hard"},
{"word": "crash ", "meaning": "와르르 무너지다, 충돌하다", "difficulty": "hard"},
{"word": "burst ", "meaning": "폭발하다, 파열하다/ 폭발, 파열", "difficulty": "hard"},
{"word": "lure", "meaning": "유혹하다/유혹물, 매력", "difficulty": "hard"},
{"word": "implore", "meaning": "애원하다, 탄원하다", "difficulty": "hard"},
{"word": "stroll", "meaning": "한가롭게 거닐다/ 산책", "difficulty": "hard"},
{"word": "stoop", "meaning": "(몸을) 구부리다/ 구부린자세", "difficulty": "hard"},
{"word": "disdain", "meaning": "경멸(하다)", "difficulty": "hard"},
{"word": "retort", "meaning": "반박(하다), 말대꾸(하다)", "difficulty": "hard"},
{"word": "education ", "meaning": "교육                                                                           ", "difficulty": "hard"},
{"word": "conduct ", "meaning": "행위, 지도", "difficulty": "hard"},
{"word": "prey ", "meaning": "먹이, 희생", "difficulty": "hard"},
{"word": "landscape ", "meaning": "풍경, 경치", "difficulty": "hard"},
{"word": "ancestor ", "meaning": "선조", "difficulty": "hard"},
{"word": "offspring", "meaning": "자손, 소산", "difficulty": "hard"},
{"word": "gwoth", "meaning": "성장, 발전", "difficulty": "hard"},
{"word": "orbit", "meaning": "(천체의)궤도 / 궤도에진입시키다", "difficulty": "hard"},
{"word": "channel", "meaning": "해협, 경로", "difficulty": "hard"},
{"word": "justice ", "meaning": "정의, 공정 ", "difficulty": "hard"},
{"word": "theme ", "meaning": "주제, 제목", "difficulty": "hard"},
{"word": "routine ", "meaning": "일상적인 일/ 틀에 박힌 ", "difficulty": "hard"},
{"word": "protest ", "meaning": "항의(하다), 주장(하다)", "difficulty": "hard"},
{"word": "tendency ", "meaning": "경향", "difficulty": "hard"},
{"word": "prophecy ", "meaning": "예언 ", "difficulty": "hard"},
{"word": "role ", "meaning": "역할", "difficulty": "hard"},
{"word": "origin ", "meaning": "기원, 태생", "difficulty": "hard"},
{"word": "process ", "meaning": "경과, 과정", "difficulty": "hard"},
{"word": "agriculture", "meaning": "농업", "difficulty": "hard"},
{"word": "skyscraper      ", "meaning": "고층건물", "difficulty": "hard"},
{"word": "nuisance ", "meaning": "방해물, 성가신 것", "difficulty": "hard"},
{"word": "vote ", "meaning": "투표(하다) ", "difficulty": "hard"},
{"word": "spur ", "meaning": "박차(를 가하다), 자극(하다)", "difficulty": "hard"},
{"word": "average ", "meaning": "평균(의)", "difficulty": "hard"},
{"word": "category ", "meaning": "범주", "difficulty": "hard"},
{"word": "doom ", "meaning": "운명, 파멸/ 운명짓다", "difficulty": "hard"},
{"word": "utility ", "meaning": "유익, 효용, 공익설비", "difficulty": "hard"},
{"word": "slavery ", "meaning": "노예제도 ", "difficulty": "hard"},
{"word": "antipathy ", "meaning": "반감 ", "difficulty": "hard"},
{"word": "caution ", "meaning": "조심, 경고 ", "difficulty": "hard"},
{"word": "reaction ", "meaning": "반동, 반응", "difficulty": "hard"},
{"word": "atmosphere ", "meaning": "분위기, 대기 ", "difficulty": "hard"},
{"word": "satellite ", "meaning": "위성 #형 위성의", "difficulty": "hard"},
{"word": "tumult", "meaning": "소동", "difficulty": "hard"},
{"word": "sage  ", "meaning": "현인, 성인 #형 현명한 ", "difficulty": "hard"},
{"word": "excess ", "meaning": "초과, 과잉 ", "difficulty": "hard"},
{"word": "architecture ", "meaning": "건축(술)", "difficulty": "hard"},
{"word": "prose ", "meaning": "산문", "difficulty": "hard"},
{"word": "temperature ", "meaning": "온도", "difficulty": "hard"},
{"word": "purchase ", "meaning": "구입(물), 획득 #타 구입하다, 획득하다", "difficulty": "hard"},
{"word": "posterity", "meaning": "자손, 후세 사람들", "difficulty": "hard"},
{"word": "heir ", "meaning": "상속인, 후계자", "difficulty": "hard"},
{"word": "applause ", "meaning": "박수갈채, 칭찬", "difficulty": "hard"},
{"word": "usage ", "meaning": "용법, 어법, 습관", "difficulty": "hard"},
{"word": "witness ", "meaning": "증거, 증인, 목격자 ", "difficulty": "hard"},
{"word": "anarchy  ", "meaning": "무정부 상태", "difficulty": "hard"},
{"word": "sculpture  ", "meaning": "조각(하다)", "difficulty": "hard"},
{"word": "notion ", "meaning": "생각, 개념", "difficulty": "hard"},
{"word": "diplomacy ", "meaning": "외교(술)", "difficulty": "hard"},
{"word": "decade ", "meaning": "10년", "difficulty": "hard"},
{"word": "thermometer ", "meaning": "온도계", "difficulty": "hard"},
{"word": "institution ", "meaning": "제도, 협회 ", "difficulty": "hard"},
{"word": "exertion ", "meaning": "노력 ", "difficulty": "hard"},
{"word": "feature ", "meaning": "특징, 용모, 특집", "difficulty": "hard"},
{"word": "disguise ", "meaning": "변장(하다)", "difficulty": "hard"},
{"word": "congress ", "meaning": "회의 ", "difficulty": "hard"},
{"word": "germ ", "meaning": "세균", "difficulty": "hard"},
{"word": "algebra ", "meaning": "대수학", "difficulty": "hard"},
{"word": "geometry ", "meaning": "기하학 ", "difficulty": "hard"},
{"word": "scrutiny", "meaning": "면밀한 조사, 음미", "difficulty": "hard"},
{"word": "sojourn ", "meaning": "체류, 묵다, 체류하다", "difficulty": "hard"},
{"word": "expedition ", "meaning": "탐험(대)", "difficulty": "hard"},
{"word": "definition ", "meaning": "정의", "difficulty": "hard"},
{"word": "conflict ", "meaning": "투쟁 / 충돌하다", "difficulty": "hard"},
{"word": "disaster ", "meaning": "재해, 불행 ", "difficulty": "hard"},
{"word": "focus", "meaning": "초점", "difficulty": "hard"},
{"word": "budget ", "meaning": "예산(안)", "difficulty": "hard"},
{"word": "intercourse ", "meaning": "교제", "difficulty": "hard"},
{"word": "ceremony ", "meaning": "의식, 의례", "difficulty": "hard"},
{"word": "regret ", "meaning": "후회(하다)", "difficulty": "hard"},
{"word": "enterprise ", "meaning": "기업, 진취적 기상", "difficulty": "hard"},
{"word": "tragedy ", "meaning": "비극", "difficulty": "hard"},
{"word": "miser ", "meaning": "구두쇠", "difficulty": "hard"},
{"word": "muscle ", "meaning": "근육", "difficulty": "hard"},
{"word": "unemployment ", "meaning": "실업", "difficulty": "hard"},
{"word": "arithmetic ", "meaning": "산수, 셈", "difficulty": "hard"},
{"word": "skill ", "meaning": "숙련", "difficulty": "hard"},
{"word": "instrument ", "meaning": "기구, 수단", "difficulty": "hard"},
{"word": "equator ", "meaning": "적도", "difficulty": "hard"},
{"word": "structure ", "meaning": "구조, 건조물", "difficulty": "hard"},
{"word": "mode ", "meaning": "방법, 양식", "difficulty": "hard"},
{"word": "aristocracy ", "meaning": "귀족, 귀족정치", "difficulty": "hard"},
{"word": "zeal ", "meaning": "열심", "difficulty": "hard"},
{"word": "trial ", "meaning": "시도, 시련, 재판", "difficulty": "hard"},
{"word": "burden ", "meaning": "무거운 짐, 부담 / 짐을 지우다", "difficulty": "hard"},
{"word": "tribe ", "meaning": "종족", "difficulty": "hard"},
{"word": "realm ", "meaning": "영지, 왕국", "difficulty": "hard"},
{"word": "fright          ", "meaning": "놀람,공포", "difficulty": "hard"},
{"word": "intelligence ", "meaning": "지능, 지성, 정보", "difficulty": "hard"},
{"word": "frame ", "meaning": "구조, 골격, 틀 /  틀에 끼우다", "difficulty": "hard"},
{"word": "hobby ", "meaning": "취미", "difficulty": "hard"},
{"word": "source ", "meaning": "원천, 출처", "difficulty": "hard"},
{"word": "twilight ", "meaning": "황혼, 희미한 빛(해뜨기 전, 해진 후의)", "difficulty": "hard"},
{"word": "fever ", "meaning": "열", "difficulty": "hard"},
{"word": "relief ", "meaning": "구제, 안심, 제거", "difficulty": "hard"},
{"word": "refuge ", "meaning": "피난(처) ", "difficulty": "hard"},
{"word": "experiment ", "meaning": "실험(하다)", "difficulty": "hard"},
{"word": "expense ", "meaning": "비용, 희생", "difficulty": "hard"},
{"word": "reliance ", "meaning": "신뢰", "difficulty": "hard"},
{"word": "grief ", "meaning": "슬픔", "difficulty": "hard"},
{"word": "effect ", "meaning": "결과, 효과, 취지/ 이루다", "difficulty": "hard"},
{"word": "scope ", "meaning": "범위, 시야", "difficulty": "hard"},
{"word": "habit ", "meaning": "습관", "difficulty": "hard"},
{"word": "defence (-se) ", "meaning": "방어, 변호", "difficulty": "hard"},
{"word": "aviation ", "meaning": "비행(술), 항공(술)", "difficulty": "hard"},
{"word": "navigation ", "meaning": "운항, 항해(술), 항공(술)", "difficulty": "hard"},
{"word": "resource ", "meaning": "(pl.) 자원, 지략", "difficulty": "hard"},
{"word": "cruelty ", "meaning": "잔인", "difficulty": "hard"},
{"word": "negligence ", "meaning": "태만", "difficulty": "hard"},
{"word": "bliss ", "meaning": "더없는 행복, 환희", "difficulty": "hard"},
{"word": "contact ", "meaning": "접촉 / 접촉하다, 연락하다", "difficulty": "hard"},
{"word": "poison ", "meaning": "독(약)", "difficulty": "hard"},
{"word": "awe", "meaning": "두려움", "difficulty": "hard"},
{"word": "nutrition ", "meaning": "영양(물)", "difficulty": "hard"},
{"word": "clue ", "meaning": "단서, 실마리", "difficulty": "hard"},
{"word": "obligation ", "meaning": "의무, 책임", "difficulty": "hard"},
{"word": "reward ", "meaning": "보답, 상 / 보답하다, 상을 주다", "difficulty": "hard"},
{"word": "peer ", "meaning": "귀족, 동료 / 응시하다", "difficulty": "hard"},
{"word": "controversy ", "meaning": "논쟁", "difficulty": "hard"},
{"word": "material ", "meaning": "물질, 재료/ 물질적인", "difficulty": "hard"},
{"word": "nationality ", "meaning": "국적,국민성", "difficulty": "hard"},
{"word": "majority ", "meaning": "대다수", "difficulty": "hard"},
{"word": "personality ", "meaning": "개성, 명사", "difficulty": "hard"},
{"word": "region", "meaning": "지방", "difficulty": "hard"},
{"word": "parliament ", "meaning": "의회", "difficulty": "hard"},
{"word": "government ", "meaning": "정부, 통치", "difficulty": "hard"},
{"word": "oath ", "meaning": "맹세, 서약", "difficulty": "hard"},
{"word": "revenue ", "meaning": "세입", "difficulty": "hard"},
{"word": "explanation ", "meaning": "설명", "difficulty": "hard"},
{"word": "minister ", "meaning": "장관, 목사/ 섬기다, 봉사하다", "difficulty": "hard"},
{"word": "obstacle ", "meaning": "장애(물)", "difficulty": "hard"},
{"word": "majesty ", "meaning": "존엄, (M-)폐하", "difficulty": "hard"},
{"word": "globe ", "meaning": "구, 공, 지구", "difficulty": "hard"},
{"word": "pressure ", "meaning": "압력, 압박", "difficulty": "hard"},
{"word": "standpoint ", "meaning": "입장, 견지(=point of view)", "difficulty": "hard"},
{"word": "monument ", "meaning": "기념비, 기념물", "difficulty": "hard"},
{"word": "opponent ", "meaning": "적, 적수", "difficulty": "hard"},
{"word": "fiction ", "meaning": "소설, 꾸며낸 이야기", "difficulty": "hard"},
{"word": "detail ", "meaning": "상세, 세목/ 상세히 말하다", "difficulty": "hard"},
{"word": "solution ", "meaning": "해결, 용해", "difficulty": "hard"},
{"word": "maximum ", "meaning": "최대한(의)", "difficulty": "hard"},
{"word": "communism ", "meaning": "공산주의", "difficulty": "hard"},
{"word": "tide ", "meaning": "조수, 형세 / 극복하다", "difficulty": "hard"},
{"word": "honesty ", "meaning": "정직", "difficulty": "hard"},
{"word": "brute ", "meaning": "짐승 (=beast)", "difficulty": "hard"},
{"word": "beast ", "meaning": "짐승, 짐승같은 인간", "difficulty": "hard"},
{"word": "inspiration ", "meaning": "영감, 고취", "difficulty": "hard"},
{"word": "harm ", "meaning": "해, 해치다", "difficulty": "hard"},
{"word": "taste ", "meaning": "맛, 취미, 기호 / 맛보다, ~한 맛이 있다", "difficulty": "hard"},
{"word": "independence ", "meaning": "독립(심)", "difficulty": "hard"},
{"word": "engagement ", "meaning": "약속, 약혼, 교전", "difficulty": "hard"},
{"word": "rank ", "meaning": "열, 지위, 계급", "difficulty": "hard"},
{"word": "glacier ", "meaning": "빙하", "difficulty": "hard"},
{"word": "prairie ", "meaning": "대초원", "difficulty": "hard"},
{"word": "cradle ", "meaning": "요람, 발상지", "difficulty": "hard"},
{"word": "incident ", "meaning": "사건", "difficulty": "hard"},
{"word": "illusion", "meaning": "환영, 환상", "difficulty": "hard"},
{"word": "disillusion ", "meaning": "각성, 환멸 / 환멸을 느끼게 하다", "difficulty": "hard"},
{"word": "election ", "meaning": "선거", "difficulty": "hard"},
{"word": "gesture ", "meaning": "몸짓", "difficulty": "hard"},
{"word": "warfare ", "meaning": "전쟁, 전투", "difficulty": "hard"},
{"word": "adventure ", "meaning": "모험", "difficulty": "hard"},
{"word": "resort ", "meaning": "유흥지, 휴양지, 수단 / (수단에)호소하다", "difficulty": "hard"},
{"word": "situation ", "meaning": "위치, 상태, 정세", "difficulty": "hard"},
{"word": "immigrant", "meaning": "(외국에서 오는) 이주자", "difficulty": "hard"},
{"word": "emigrant ", "meaning": " (다른 나라로의)이주자", "difficulty": "hard"},
{"word": "historian ", "meaning": "역사가", "difficulty": "hard"},
{"word": "creature ", "meaning": "창조물, 생물", "difficulty": "hard"},
{"word": "victim ", "meaning": "희생(자)", "difficulty": "hard"},
{"word": "delight ", "meaning": "즐거움/ 즐겁게 하다", "difficulty": "hard"},
{"word": "decay ", "meaning": "부패(하다), 쇠퇴(하다)", "difficulty": "hard"},
{"word": "admiral ", "meaning": "해군대장, 제독", "difficulty": "hard"},
